{
  "backtrack_count": 1,
  "bugwood_meta": {
    "aez_climate": "subtropical_moist",
    "aez_code": "STM",
    "crop_species": "Soybean",
    "disease_name": "Soybean Rust",
    "lat": 27.766279,
    "lon": -81.686783,
    "month": 0,
    "src_path": "smoke/.bugwood_cache/5202011.jpg"
  },
  "early_terminated": true,
  "ensemble_probs": {
    "T1": {
      "Blight": 0.002535014384375128,
      "Canker": 0.0008701091406633584,
      "Lesion": 0.2733801654256386,
      "Mosaic": 0.7202608037389252,
      "Powdery mildew": 8.220726275303628e-05,
      "Rot": 0.0009481911840100903,
      "Rust": 0.0002165872899063142,
      "Wilt": 0.0017069215737284124
    },
    "T2": {
      "Bacterial": 0.5495007686735052,
      "Fungal": 0.145407827698384,
      "Nutrient deficiency": 0.044001771710929054,
      "Pest damage": 0.20187877616536407,
      "Viral": 0.059210855751817754
    },
    "T3": {},
    "T4": {
      "Early": 0.07357310265491225,
      "Healthy": 0.013662922210285902,
      "Moderate": 0.24408054075347244,
      "Severe": 0.6686834343813294
    },
    "T5": {
      "Soybean": 0.0010657421281425714,
      "Tomato": 0.9989342578718574
    }
  },
  "final_predictions": {
    "T1": "irregular, uneven appearance and possible presence of inflammation",
    "T2": "inflammatory",
    "T3": "likely indication of an inflammatory condition",
    "T4": "unspecified",
    "T5": "not applicable"
  },
  "image_id": "bugwood::5202011::run00",
  "loop_rate": 0.2857142857142857,
  "path": [
    "MorphologyAgent",
    "SymptomAgent",
    "MorphologyAgent",
    "SymptomAgent",
    "PathogenAgent",
    "SeverityAgent",
    "DiagnosisAgent"
  ],
  "path_length": 7,
  "routing_signal": "hf_direct",
  "total_tokens": 794
}